asdf_standard/__init__.py
asdf_standard/_version.py
asdf_standard/integration.py
asdf_standard/resource.py
asdf_standard/resources/manifests/asdf-format.org/astronomy/astronomy-1.0.0.yaml
asdf_standard/resources/manifests/asdf-format.org/astronomy/astronomy-1.1.0.yaml
asdf_standard/resources/manifests/asdf-format.org/astronomy/astronomy-1.2.0.yaml
asdf_standard/resources/manifests/asdf-format.org/core/core-1.0.0.yaml
asdf_standard/resources/manifests/asdf-format.org/core/core-1.1.0.yaml
asdf_standard/resources/manifests/asdf-format.org/core/core-1.2.0.yaml
asdf_standard/resources/manifests/asdf-format.org/core/core-1.3.0.yaml
asdf_standard/resources/manifests/asdf-format.org/core/core-1.4.0.yaml
asdf_standard/resources/manifests/asdf-format.org/core/core-1.5.0.yaml
asdf_standard/resources/manifests/asdf-format.org/core/core-1.6.0.yaml
asdf_standard/resources/schemas/asdf-format.org/core/extension_manifest-1.0.0.yaml
asdf_standard/resources/schemas/stsci.edu/asdf/asdf-schema-1.0.0.yaml
asdf_standard/resources/schemas/stsci.edu/asdf/asdf-schema-1.1.0.yaml
asdf_standard/resources/schemas/stsci.edu/asdf/version_map-1.0.0.yaml
asdf_standard/resources/schemas/stsci.edu/asdf/version_map-1.1.0.yaml
asdf_standard/resources/schemas/stsci.edu/asdf/version_map-1.2.0.yaml
asdf_standard/resources/schemas/stsci.edu/asdf/version_map-1.3.0.yaml
asdf_standard/resources/schemas/stsci.edu/asdf/version_map-1.4.0.yaml
asdf_standard/resources/schemas/stsci.edu/asdf/version_map-1.5.0.yaml
asdf_standard/resources/schemas/stsci.edu/asdf/version_map-1.6.0.yaml
asdf_standard/resources/schemas/stsci.edu/asdf/core/asdf-1.0.0.yaml
asdf_standard/resources/schemas/stsci.edu/asdf/core/asdf-1.1.0.yaml
asdf_standard/resources/schemas/stsci.edu/asdf/core/column-1.0.0.yaml
asdf_standard/resources/schemas/stsci.edu/asdf/core/complex-1.0.0.yaml
asdf_standard/resources/schemas/stsci.edu/asdf/core/constant-1.0.0.yaml
asdf_standard/resources/schemas/stsci.edu/asdf/core/datatype-1.0.0.yaml
asdf_standard-1.4.0.dist-info/licenses/LICENSE
asdf_standard-1.4.0.dist-info/METADATA
asdf_standard-1.4.0.dist-info/WHEEL
asdf_standard-1.4.0.dist-info/entry_points.txt
asdf_standard-1.4.0.dist-info/top_level.txt
asdf_standard-1.4.0.dist-info/RECORD
