Metadata-Version: 2.4
Name: asdf_standard
Version: 1.4.0
Summary: The ASDF Standard schemas
Author-email: The ASDF Developers <help@stsci.edu>
Project-URL: tracker, https://github.com/asdf-format/asdf-standard/issues
Project-URL: documentation, https://www.asdf-format.org/projects/asdf-standard/en/latest
Project-URL: repository, https://github.com/asdf-format/asdf-standard
Classifier: Programming Language :: Python
Classifier: Programming Language :: Python :: 3
Classifier: Development Status :: 5 - Production/Stable
Requires-Python: >=3.9
License-File: LICENSE
Provides-Extra: docs
Requires-Dist: tomli; extra == "docs"
Requires-Dist: sphinx>=4.0; extra == "docs"
Requires-Dist: sphinx-asdf>=0.1.3; extra == "docs"
Requires-Dist: graphviz; extra == "docs"
Requires-Dist: matplotlib; extra == "docs"
Requires-Dist: docutils; extra == "docs"
Requires-Dist: furo; extra == "docs"
Provides-Extra: test
Requires-Dist: pytest; extra == "test"
Requires-Dist: pytest-asdf-plugin; extra == "test"
Requires-Dist: pyyaml; extra == "test"
Requires-Dist: asdf>=3.0.0; extra == "test"
Requires-Dist: packaging>=16.0; extra == "test"
Dynamic: license-file
